hedera_agent_kit/__init__.py
hedera_agent_kit/langchain/__init__.py
hedera_agent_kit/langchain/response_parser_service.py
hedera_agent_kit/langchain/tool.py
hedera_agent_kit/langchain/toolkit.py
hedera_agent_kit/mcp/__init__.py
hedera_agent_kit/mcp/toolkit.py
hedera_agent_kit/plugins/__init__.py
hedera_agent_kit/plugins/core_account_plugin/__init__.py
hedera_agent_kit/plugins/core_account_plugin/approve_fungible_token_allowance.py
hedera_agent_kit/plugins/core_account_plugin/approve_hbar_allowance.py
hedera_agent_kit/plugins/core_account_plugin/approve_non_fungible_token_allowance.py
hedera_agent_kit/plugins/core_account_plugin/create_account.py
hedera_agent_kit/plugins/core_account_plugin/delete_account.py
hedera_agent_kit/plugins/core_account_plugin/delete_hbar_allowance.py
hedera_agent_kit/plugins/core_account_plugin/schedule_delete.py
hedera_agent_kit/plugins/core_account_plugin/sign_schedule_transaction.py
hedera_agent_kit/plugins/core_account_plugin/transfer_hbar.py
hedera_agent_kit/plugins/core_account_plugin/transfer_hbar_with_allowance.py
hedera_agent_kit/plugins/core_account_plugin/update_account.py
hedera_agent_kit/plugins/core_account_query_plugin/__init__.py
hedera_agent_kit/plugins/core_account_query_plugin/get_account_query.py
hedera_agent_kit/plugins/core_account_query_plugin/get_hbar_balance.py
hedera_agent_kit/plugins/core_account_query_plugin/get_token_balances.py
hedera_agent_kit/plugins/core_consensus_plugin/__init__.py
hedera_agent_kit/plugins/core_consensus_plugin/create_topic.py
hedera_agent_kit/plugins/core_consensus_plugin/delete_topic.py
hedera_agent_kit/plugins/core_consensus_plugin/submit_topic_message.py
hedera_agent_kit/plugins/core_consensus_plugin/update_topic.py
hedera_agent_kit/plugins/core_consensus_query_plugin/__init__.py
hedera_agent_kit/plugins/core_consensus_query_plugin/get_topic_info_query.py
hedera_agent_kit/plugins/core_consensus_query_plugin/get_topic_messages_query.py
hedera_agent_kit-3.2.0.dist-info/METADATA
hedera_agent_kit-3.2.0.dist-info/WHEEL
hedera_agent_kit-3.2.0.dist-info/RECORD
