Metadata-Version: 2.4
Name: hedera-agent-kit
Version: 3.2.0
Summary: Use the Hedera Agent Kit to build agents that can interact with the Hedera network in any framework you like
License: Apache-2.0
Author: Hashgraph
Requires-Python: >=3.10,<3.14
Classifier: License :: OSI Approved :: Apache Software License
Classifier: Programming Language :: Python :: 3
Classifier: Programming Language :: Python :: 3.10
Classifier: Programming Language :: Python :: 3.11
Classifier: Programming Language :: Python :: 3.12
Classifier: Programming Language :: Python :: 3.13
Requires-Dist: aiohttp (>=3.13.1,<4.0.0)
Requires-Dist: hiero-sdk-python (==0.1.9)
Requires-Dist: langchain (==1.2.0)
Requires-Dist: langchain-anthropic (==1.3.0)
Requires-Dist: langchain-groq (==1.1.1)
Requires-Dist: langchain-openai (==1.1.6)
Requires-Dist: mcp (==1.25.0)
Requires-Dist: pydantic (>=2.12.3,<3.0.0)
Requires-Dist: python-dotenv (>=1,<2)
Requires-Dist: web3 (==7.14.0)
